mcot/__init__.py
mcot/dippi/README.rst
mcot/dippi/VERSION
mcot/dippi/__init__.py
mcot/dippi/model.py
mcot/dippi/scan.py
mcot/dippi/simulator.py
mcot/dippi/geometry/__init__.py
mcot/dippi/geometry/cylinders.py
mcot.dippi-0.1.2.dist-info/METADATA
mcot.dippi-0.1.2.dist-info/WHEEL
mcot.dippi-0.1.2.dist-info/namespace_packages.txt
mcot.dippi-0.1.2.dist-info/top_level.txt
mcot.dippi-0.1.2.dist-info/RECORD
